typebuf/__init__.py
typebuf/fs.py
typebuf/lib.py
typebuf/models/ir.py
typebuf/models/typedefinition.py
typebuf/models/typefield.py
typebuf/transformers/__init__.py
typebuf/transformers/base.py
typebuf/transformers/python.py
typebuf/transformers/typescript.py
typebuf-0.1.4.dist-info/entry_points.txt
typebuf-0.1.4.dist-info/LICENSE.txt
typebuf-0.1.4.dist-info/WHEEL
typebuf-0.1.4.dist-info/METADATA
typebuf-0.1.4.dist-info/RECORD
