Metadata-Version: 2.1
Name: typebuf
Version: 0.1.4
Summary: Dead simple way to define shared type definitions between applications
Home-page: https://github.com/shanahanjrs/typebuf
License: Apache-2.0
Author: John Shanahan
Author-email: shanahan.jrs@gmail.com
Requires-Python: >=3.9,<4.0
Classifier: License :: OSI Approved :: Apache Software License
Classifier: Programming Language :: Python :: 3
Classifier: Programming Language :: Python :: 3.9
Classifier: Topic :: Software Development :: Build Tools
Classifier: Topic :: Software Development :: Libraries :: Python Modules
Requires-Dist: PyYAML (>=6.0,<7.0)
Requires-Dist: click (>=8.0.3,<9.0.0)
Requires-Dist: pydantic (>=1.8.2,<2.0.0)
Project-URL: Documentation, https://github.com/shanahanjrs/typebuf/blob/master/README.md#documentation
Project-URL: Repository, https://github.com/shanahanjrs/typebuf
